.zenodo.json
AUTHORS.rst
CITATION
CONTRIBUTING.rst
HISTORY.rst
LICENSE
Makefile
README.rst
pyproject.toml
tox.ini
enpt/__init__.py
enpt/cli.py
enpt/version.py
enpt.egg-info/PKG-INFO
enpt.egg-info/SOURCES.txt
enpt.egg-info/dependency_links.txt
enpt.egg-info/entry_points.txt
enpt.egg-info/not-zip-safe
enpt.egg-info/requires.txt
enpt.egg-info/top_level.txt
enpt/execution/__init__.py
enpt/execution/controller.py
enpt/io/__init__.py
enpt/io/reader.py
enpt/model/__init__.py
enpt/model/srf.py
enpt/model/images/__init__.py
enpt/model/images/image_baseclasses.py
enpt/model/images/images_mapgeo.py
enpt/model/images/images_sensorgeo.py
enpt/model/metadata/__init__.py
enpt/model/metadata/metadata_mapgeo.py
enpt/model/metadata/metadata_sensorgeo.py
enpt/options/__init__.py
enpt/options/config.py
enpt/options/options_default.json
enpt/options/options_schema.py
enpt/processors/__init__.py
enpt/processors/atmospheric_correction/__init__.py
enpt/processors/atmospheric_correction/atmospheric_correction.py
enpt/processors/cloud_screening/__init__.py
enpt/processors/cloud_screening/cloud_screening.py
enpt/processors/dead_pixel_correction/__init__.py
enpt/processors/dead_pixel_correction/dead_pixel_correction.py
enpt/processors/dem_preprocessing/__init__.py
enpt/processors/dem_preprocessing/dem_preprocessing.py
enpt/processors/image_correction/__init__.py
enpt/processors/image_correction/image_correction.py
enpt/processors/orthorectification/__init__.py
enpt/processors/orthorectification/orthorectification.py
enpt/processors/radiometric_transform/__init__.py
enpt/processors/radiometric_transform/radiometric_transform.py
enpt/processors/spatial_module/__init__.py
enpt/processors/spatial_module/spatial_module.py
enpt/processors/spatial_optimization/__init__.py
enpt/processors/spatial_optimization/spatial_optimization.py
enpt/processors/spatial_transform/__init__.py
enpt/processors/spatial_transform/spatial_transform.py
enpt/resources/EnMAP_Sensor/EnMAP_Level_1B_SNR.zip
enpt/resources/earth_sun_distance/Earth_Sun_distances_per_day_edited__1980_2030.csv
enpt/resources/solar_irradiance/SUNp1fontenla__350-2500nm_@0.1nm_converted.txt
enpt/utils/__init__.py
enpt/utils/logging.py
