Metadata-Version: 2.4
Name: enpt
Version: 0.21.1
Summary: EnMAP Processing Tool
Author-email: Daniel Scheffler <daniel.scheffler@gfz-potsdam.de>, Niklas Bohn <nbohn@gfz-potsdam.de>, Stéphane Guillaso <stephane.guillaso@gfz-potsdam.de>, Brenner Silva <brenner.silva@awi.de>, Leonardo Alvarado <leonardo.alvarado@awi.de>, Karl Segl <segl@gfz-potsdam.de>
Maintainer-email: Daniel Scheffler <daniel.scheffler@gfz-potsdam.de>
License: GPL-3.0-or-later
Project-URL: Source code, https://git.gfz-potsdam.de/EnMAP/GFZ_Tools_EnMAP_BOX/EnPT
Project-URL: Issue Tracker, https://git.gfz-potsdam.de/EnMAP/GFZ_Tools_EnMAP_BOX/EnPT/-/issues
Project-URL: Documentation, https://enmap.git-pages.gfz-potsdam.de/GFZ_Tools_EnMAP_BOX/EnPT/doc
Project-URL: Change log, https://git.gfz-potsdam.de/EnMAP/GFZ_Tools_EnMAP_BOX/EnPT/-/blob/main/HISTORY.rst
Project-URL: Zenodo, https://zenodo.org/records/8229436
Keywords: EnPT,EnMAP,EnMAP-Box,hyperspectral,remote sensing,satellite,processing chain
Classifier: Development Status :: 4 - Beta
Classifier: License :: OSI Approved :: GNU General Public License v3 or later (GPLv3+)
Classifier: Natural Language :: English
Classifier: Programming Language :: Python :: 3.8
Classifier: Programming Language :: Python :: 3.9
Classifier: Programming Language :: Python :: 3.10
Classifier: Programming Language :: Python :: 3.11
Requires-Python: >=3.8
License-File: LICENSE
Requires-Dist: acwater>=0.3.0
Requires-Dist: arosics>=1.0.0
Requires-Dist: cerberus
Requires-Dist: gdal
Requires-Dist: geoarray>=0.15.8
Requires-Dist: jsmin
Requires-Dist: lxml
Requires-Dist: matplotlib
Requires-Dist: mvgavg
Requires-Dist: natsort
Requires-Dist: numpy
Requires-Dist: numpy-indexed
Requires-Dist: packaging
Requires-Dist: pandas
Requires-Dist: py_tools_ds>=0.14.25
Requires-Dist: pyproj>=3.4.0
Requires-Dist: scikit-image
Requires-Dist: scipy
Requires-Dist: sensormapgeo>=1.0.0
Requires-Dist: sicor>=0.19.1
Requires-Dist: tqdm
Requires-Dist: utm
Provides-Extra: doc
Requires-Dist: sphinx-argparse; extra == "doc"
Requires-Dist: sphinx_rtd_theme; extra == "doc"
Provides-Extra: test
Requires-Dist: pytest; extra == "test"
Requires-Dist: pytest-cov; extra == "test"
Requires-Dist: pytest-reporter-html1; extra == "test"
Requires-Dist: urlchecker; extra == "test"
Provides-Extra: lint
Requires-Dist: flake8; extra == "lint"
Requires-Dist: pycodestyle; extra == "lint"
Requires-Dist: pydocstyle; extra == "lint"
Provides-Extra: dev
Requires-Dist: enpt[test]; extra == "dev"
Requires-Dist: enpt[doc]; extra == "dev"
Requires-Dist: enpt[lint]; extra == "dev"
Dynamic: license-file
